Metadata-Version: 1.1
Name: mprint-assistant
Version: 0.3
Summary: Easy printing to U of M printers
Home-page: https://github.com/samharad/mprint-assistant
Author: Sam Adams
Author-email: sam.h.adams@gmail.com
License: MIT
Keywords: Michigan print mprint
Platform: UNKNOWN
Classifier: Development Status :: 3 - Alpha
Classifier: Intended Audience :: Other Audience
Classifier: License :: OSI Approved :: MIT License
Classifier: Programming Language :: Python :: 2.7
Classifier: Programming Language :: Python :: 3
Classifier: Topic :: Printing
